README.md
setup.py
src/non_api/__init__.py
src/non_api/convert_df.py
src/non_api/html_to_df.py
src/non_api/non_api.py
src/non_api.egg-info/PKG-INFO
src/non_api.egg-info/SOURCES.txt
src/non_api.egg-info/dependency_links.txt
src/non_api.egg-info/requires.txt
src/non_api.egg-info/top_level.txt